spotify_autopush/README.md
spotify_autopush/__main__.py
spotify_autopush/main.py
spotify_autopush/src/models/env_loader.py
spotify_autopush/src/models/github.py
spotify_autopush/src/models/spotify.py
spotify_autopush-1.0.0.dist-info/LICENSE
spotify_autopush-1.0.0.dist-info/METADATA
spotify_autopush-1.0.0.dist-info/WHEEL
spotify_autopush-1.0.0.dist-info/entry_points.txt
spotify_autopush-1.0.0.dist-info/RECORD
