Metadata-Version: 2.1
Name: spotify_autopush
Version: 1.0.0
Summary: Display on your Github profile your last played album to show the world your great musical tastes
Author: Arthur Broudoux
Author-email: arthur.broudoux@gmail.com
Requires-Python: >=3.12,<4.0
Classifier: Programming Language :: Python :: 3
Classifier: Programming Language :: Python :: 3.12
Requires-Dist: python-dotenv (>=1.0.0,<2.0.0)
Requires-Dist: requests (>=2.31.0,<3.0.0)
Requires-Dist: spotipy (>=2.19.0,<3.0.0)
